fog05mm1/__init__.py
fog05mm1/apimm1.py
fog05mm1-0.0.1.dist-info/DESCRIPTION.rst
fog05mm1-0.0.1.dist-info/METADATA
fog05mm1-0.0.1.dist-info/RECORD
fog05mm1-0.0.1.dist-info/WHEEL
fog05mm1-0.0.1.dist-info/metadata.json
fog05mm1-0.0.1.dist-info/top_level.txt
