Metadata-Version: 2.0
Name: fog05mm1
Version: 0.0.1
Summary: Eclipse fog05 Mm1 REST Client API
Home-page: https://github.com/eclipse/fog05
Author: ADLINK
Author-email: UNKNOWN
License: Apache 2.O or EPL 2.0
Platform: UNKNOWN
Classifier: Development Status :: 2 - Pre-Alpha
Classifier: Intended Audience :: Developers
Classifier: Intended Audience :: Telecommunications Industry
Classifier: License :: OSI Approved :: Apache Software License
Classifier: License :: OSI Approved :: Eclipse Public License 2.0 (EPL-2.0)
Classifier: Programming Language :: Python :: 2
Classifier: Programming Language :: Python :: 3
Requires-Dist: requests
